glife/__init__.py
glife/abstract/__init__.py
glife/abstract/gol_interface.py
glife/api/__init__.py
glife/api/app.py
glife/cli/__init__.py
glife/cli/arguments.py
glife/cli/cli.py
glife/cli/start_field/__init__.py
glife/cli/start_field/from_file.py
glife/cli/start_field/only_string.py
glife/cli/start_field/string_with_width.py
glife/colony/__init__.py
glife/colony/colony.py
glife/colony/colony_state.py
glife/colony/exception/__init__.py
glife/colony/exception/colony_exception.py
glife/colony/tests/__init__.py
glife/colony/tests/test_colony.py
glife/gol/__init__.py
glife/gol/api.py
glife/gol/arguments.py
glife/gol/factory.py
glife/gol/field.py
glife/gol/point.py
glife/gol/rules_interface.py
glife/gol/rules/__init__.py
glife/gol/rules/conway.py
glife/gol/tests/__init__.py
glife/gol/tests/test_api.py
glife/gol/tests/test_field.py
glife/gol/tests/rules/__init__.py
glife/gol/tests/rules/test_conway.py
glife-0.2.dist-info/METADATA
glife-0.2.dist-info/WHEEL
glife-0.2.dist-info/entry_points.txt
glife-0.2.dist-info/top_level.txt
glife-0.2.dist-info/RECORD
