Metadata-Version: 2.1
Name: glife
Version: 0.2
Summary: UNKNOWN
Home-page: https://github.com/lbacik/glife
Author: Łukasz Bacik
Author-email: mail@luka.sh
License: GPLv3
Platform: UNKNOWN
Classifier: Environment :: Console
Classifier: Operating System :: OS Independent
Classifier: Programming Language :: Python
Requires-Dist: simple-value-object
